{
  "recentFiles": [
    {
      "basename": "Games - The Data Side",
      "path": "docs/blog/posts/Games - The Data Side.md"
    },
    {
      "basename": "Taming Project Complexity",
      "path": "docs/blog/posts/Taming Project Complexity.md"
    },
    {
      "basename": "Zettelkasten, Wiki, and Beyond",
      "path": "docs/blog/posts/Zettelkasten, Wiki, and Beyond.md"
    },
    {
      "basename": "Translating PDF Documents",
      "path": "docs/Translating PDF Documents.md"
    },
    {
      "basename": "CircusWiki - Technical Manual",
      "path": "_inbox/CircusWiki - Technical Manual.md"
    },
    {
      "basename": "Screenshot-Google-AiStudio-Translation",
      "path": "docs/img/Screenshot-Google-AiStudio-Translation.png"
    },
    {
      "basename": "Screenshot-Google-AiStudio-Transcription",
      "path": "docs/img/Screenshot-Google-AiStudio-Transcription.png"
    },
    {
      "basename": "Kaskade 001",
      "path": "docs/Kaskade 001.md"
    },
    {
      "basename": "nica-logo-simple-small-150x150",
      "path": "docs/img/nica-logo-simple-small-150x150.png"
    },
    {
      "basename": "README",
      "path": "README.md"
    },
    {
      "basename": "Presentation Wiki Project",
      "path": "_inbox/Presentation Wiki Project.md"
    },
    {
      "basename": "Hallo ich bin - mit Bällen",
      "path": "docs/Hallo ich bin - mit Bällen.md"
    },
    {
      "basename": "doc-sys-2",
      "path": "docs/doc-sys-2.md"
    },
    {
      "basename": "Spiele zum Kennenlernen",
      "path": "docs/Spiele zum Kennenlernen.md"
    },
    {
      "basename": "Bällewirrwarr",
      "path": "docs/Bällewirrwarr.md"
    },
    {
      "basename": "Bewegungs-Spiele",
      "path": "docs/Bewegungs-Spiele.md"
    },
    {
      "basename": "Alaska Baseball",
      "path": "docs/Alaska Baseball.md"
    },
    {
      "basename": "Aufwärmspiele MOC",
      "path": "docs/Aufwärmspiele MOC.md"
    },
    {
      "basename": "Eisbär auf der Scholle",
      "path": "docs/Eisbär auf der Scholle.md"
    },
    {
      "basename": "Der Hund im großen Haus",
      "path": "docs/Der Hund im großen Haus.md"
    },
    {
      "basename": "Spiele yaml check",
      "path": "_dataview/Spiele yaml check.md"
    },
    {
      "basename": "Fangspiele",
      "path": "docs/Fangspiele.md"
    },
    {
      "basename": "Adler Hase Kohlkopf",
      "path": "docs/Adler Hase Kohlkopf.md"
    },
    {
      "basename": "Zombie Hasche mit Namen",
      "path": "docs/Zombie Hasche mit Namen.md"
    },
    {
      "basename": "Zombie - Hasche",
      "path": "docs/Zombie - Hasche.md"
    },
    {
      "basename": "Zeithasche",
      "path": "docs/Zeithasche.md"
    },
    {
      "basename": "Tellerfänger",
      "path": "docs/Tellerfänger.md"
    },
    {
      "basename": "Schwänzchen-Hasche",
      "path": "docs/Schwänzchen-Hasche.md"
    },
    {
      "basename": "Robbe und Eisbären",
      "path": "docs/Robbe und Eisbären.md"
    },
    {
      "basename": "Popcorn",
      "path": "docs/Popcorn.md"
    },
    {
      "basename": "Pinguine und Killer-Flamingos",
      "path": "docs/Pinguine und Killer-Flamingos.md"
    },
    {
      "basename": "Pinguine und Eisbären",
      "path": "docs/Pinguine und Eisbären.md"
    },
    {
      "basename": "index",
      "path": "docs/index.md"
    },
    {
      "basename": "index",
      "path": "docs/blog/index.md"
    },
    {
      "basename": "index",
      "path": "translation_test/en/index.md"
    },
    {
      "basename": "index",
      "path": "translation_test/index.md"
    },
    {
      "basename": "Möhre Hase Fuchs",
      "path": "docs/Möhre Hase Fuchs.md"
    },
    {
      "basename": "Luftballon Hasche",
      "path": "docs/Luftballon Hasche.md"
    },
    {
      "basename": "Zombieball",
      "path": "docs/Zombieball.md"
    },
    {
      "basename": "Mittelalter Schnick Schnack Schnuck",
      "path": "docs/Mittelalter Schnick Schnack Schnuck.md"
    },
    {
      "basename": "Komm mit, lauf weg",
      "path": "docs/Komm mit, lauf weg.md"
    },
    {
      "basename": "Ich habe Glück",
      "path": "docs/Ich habe Glück.md"
    },
    {
      "basename": "Fuchsjagd",
      "path": "docs/Fuchsjagd.md"
    },
    {
      "basename": "Fuchs und Hase",
      "path": "docs/Fuchs und Hase.md"
    },
    {
      "basename": "Festnageln",
      "path": "docs/Festnageln.md"
    },
    {
      "basename": "Farbenhasche",
      "path": "docs/Farbenhasche.md"
    },
    {
      "basename": "Bombenspiel",
      "path": "docs/Bombenspiel.md"
    },
    {
      "basename": "5 Drachen und Zwerge",
      "path": "docs/5 Drachen und Zwerge.md"
    },
    {
      "basename": "Vorstellungsrunde - Werdegang - Symbolisch",
      "path": "docs/Vorstellungsrunde - Werdegang - Symbolisch.md"
    },
    {
      "basename": "Suchkind",
      "path": "docs/Suchkind.md"
    }
  ],
  "omittedPaths": [],
  "omittedTags": [],
  "updateOn": "file-open",
  "omitBookmarks": false
}